tgedr/connectors/__init__.py
tgedr/connectors/azure_ad.py
tgedr/connectors/azure_table_storage.py
tgedr/connectors/common.py
tgedr/connectors/ftp.py
tgedr/connectors/monetate_api.py
tgedr_connectors-0.0.6.dist-info/LICENSE
tgedr_connectors-0.0.6.dist-info/METADATA
tgedr_connectors-0.0.6.dist-info/WHEEL
tgedr_connectors-0.0.6.dist-info/top_level.txt
tgedr_connectors-0.0.6.dist-info/RECORD
